ampel/contrib/hu/alert/DynamicShaperAlertConsumer.py
ampel/contrib/hu/alert/NeoWisePhotometryAlertSupplier.py
ampel/contrib/hu/alert/ResourceDependentConsumer.py
ampel/contrib/hu/alert/load/WiseFileAlertLoader.py
ampel/contrib/hu/channel_notes.txt
ampel/contrib/hu/ingest/ZiGWDataPointShaper.py
ampel/contrib/hu/py.typed
ampel/contrib/hu/t0/LensedTransientFilter.py
ampel/contrib/hu/t0/PredetectionFilter.py
ampel/contrib/hu/t0/RandFilter.py
ampel/contrib/hu/t0/RcfFilter.py
ampel/contrib/hu/t0/RedshiftCatalogFilter.py
ampel/contrib/hu/t0/SimpleDecentFilter.py
ampel/contrib/hu/t0/StellarFilter.py
ampel/contrib/hu/t0/TransientInClusterFilter.py
ampel/contrib/hu/t0/XShooterFilter.py
ampel/contrib/hu/t2/T2BaseClassifier.py
ampel/contrib/hu/t2/T2BaseLightcurveFitter.py
ampel/contrib/hu/t2/T2BayesianBlocks.py
ampel/contrib/hu/t2/T2BrightSNProb.py
ampel/contrib/hu/t2/T2CatalogMatchLocal.py
ampel/contrib/hu/t2/T2DemoLightcurveFitter.py
ampel/contrib/hu/t2/T2DigestRedshifts.py
ampel/contrib/hu/t2/T2DustEchoEval.py
ampel/contrib/hu/t2/T2ElasticcRedshiftSampler.py
ampel/contrib/hu/t2/T2ElasticcReport.py
ampel/contrib/hu/t2/T2FastDecliner.py
ampel/contrib/hu/t2/T2GetLensSNParameters.py
ampel/contrib/hu/t2/T2HealpixProb.py
ampel/contrib/hu/t2/T2InfantCatalogEval.py
ampel/contrib/hu/t2/T2KilonovaEval.py
ampel/contrib/hu/t2/T2KilonovaStats.py
ampel/contrib/hu/t2/T2LCQuality.py
ampel/contrib/hu/t2/T2LSPhotoZTap.py
ampel/contrib/hu/t2/T2LoadRedshift.py
ampel/contrib/hu/t2/T2MatchBTS.py
ampel/contrib/hu/t2/T2MatchGRB.py
ampel/contrib/hu/t2/T2MinorPlanetCenter.py
ampel/contrib/hu/t2/T2MultiXgbClassifier.py
ampel/contrib/hu/t2/T2NedSNCosmo.py
ampel/contrib/hu/t2/T2NedTap.py
ampel/contrib/hu/t2/T2Observability.py
ampel/contrib/hu/t2/T2PS1ThumbExtCat.py
ampel/contrib/hu/t2/T2PS1ThumbNedSNCosmo.py
ampel/contrib/hu/t2/T2PS1ThumbNedTap.py
ampel/contrib/hu/t2/T2PanStarrThumbPrint.py
ampel/contrib/hu/t2/T2PhaseLimit.py
ampel/contrib/hu/t2/T2PolynomialFit.py
ampel_hu_astro-0.8.4.post0.dist-info/LICENSE
ampel_hu_astro-0.8.4.post0.dist-info/METADATA
ampel_hu_astro-0.8.4.post0.dist-info/WHEEL
ampel_hu_astro-0.8.4.post0.dist-info/RECORD
