Metadata-Version: 2.1
Name: ampel-hu-astro
Version: 0.8.4.post0
Summary: Astronomy units for the Ampel system from HU-Berlin
Home-page: https://ampelproject.github.io
License: BSD-3-Clause
Author: Valery Brinnel
Requires-Python: >=3.10,<3.12
Classifier: Development Status :: 4 - Beta
Classifier: Intended Audience :: Science/Research
Classifier: License :: OSI Approved :: BSD License
Classifier: Programming Language :: Python :: 3
Classifier: Programming Language :: Python :: 3.10
Classifier: Programming Language :: Python :: 3.11
Classifier: Topic :: Scientific/Engineering :: Information Analysis
Classifier: Typing :: Typed
Provides-Extra: elasticc
Provides-Extra: extcats
Provides-Extra: legacy-surveys
Provides-Extra: ligo
Provides-Extra: notebook
Provides-Extra: panstarrs
Provides-Extra: slack
Provides-Extra: sncosmo
Provides-Extra: snpy
Provides-Extra: voevent
Provides-Extra: ztf
Requires-Dist: adjustText (>=1.0.0,<2.0.0)
Requires-Dist: ampel-alerts (>=0.8.5,<0.9)
Requires-Dist: ampel-interface (>=0.8.8,<0.9)
Requires-Dist: ampel-lsst (>=0.8.6,<0.9) ; extra == "elasticc"
Requires-Dist: ampel-photometry (>=0.8.3,<0.9)
Requires-Dist: ampel-plot (>=0.8.3-3,<0.9)
Requires-Dist: ampel-ztf[kafka] (>=0.8.13,<0.9) ; extra == "ligo" or extra == "ztf"
Requires-Dist: astro-datalab (>=2,<3) ; extra == "legacy-surveys"
Requires-Dist: astro-parsnip (>=1.4.1,<2.0.0) ; extra == "elasticc"
Requires-Dist: astropy (>=5.0)
Requires-Dist: backoff (>=2,<3)
Requires-Dist: beautifulsoup4 (>=4.10.0,<5.0.0)
Requires-Dist: extcats (>=2.4.2,<3.0.0) ; extra == "extcats"
Requires-Dist: healpy (>=1.16.2,<2.0.0) ; extra == "ligo"
Requires-Dist: iminuit (>=2.8.0,<3.0.0) ; extra == "ligo" or extra == "sncosmo"
Requires-Dist: jupyter (>=1.0.0,<2.0.0) ; extra == "notebook"
Requires-Dist: light-curve (>=0.7.3,<0.8.0)
Requires-Dist: ligo-gracedb (>=2.12.0,<3.0.0) ; extra == "ligo"
Requires-Dist: more-itertools (>=10.0.0,<11.0.0)
Requires-Dist: numpy (>=1,<2)
Requires-Dist: pandas (>=2.0)
Requires-Dist: pymage (>=0.5,<0.6) ; extra == "panstarrs"
Requires-Dist: requests (>=2.26.0,<3.0.0)
Requires-Dist: scikit-learn (>=1.1.3,<2.0.0)
Requires-Dist: scipy (>=1.4)
Requires-Dist: seaborn (>=0.12.0,<0.13.0)
Requires-Dist: sfdmap2 (>=0.2.0,<0.3.0) ; extra == "ligo" or extra == "sncosmo"
Requires-Dist: slack-sdk (>=3,<4) ; extra == "slack"
Requires-Dist: sncosmo (>=2.5.0,<3.0.0) ; extra == "ligo" or extra == "sncosmo"
Requires-Dist: snpy (>=2.5.3,<3.0.0) ; extra == "snpy"
Requires-Dist: timeout-decorator (>=0.5,<0.6) ; extra == "elasticc"
Requires-Dist: uncertainties (>=3.1.7,<4.0.0)
Requires-Dist: voevent-parse (>=1.0.3,<2.0.0) ; extra == "voevent"
Requires-Dist: xgboost (>=1.6.2,<2.0.0) ; extra == "elasticc"
Requires-Dist: ztfquery (>=1.26.1,<2.0.0) ; extra == "ztf"
Project-URL: Repository, https://github.com/AmpelProject/Ampel-HU-astro
